[
  {
    "customer": {
      "name": "zaid-bwp-wa-bot2",
      "mobile": "+1",
      "email": "hasilpurofficial4@gmail.com",
      "address": "shan0987654.uk@gmail.com",
      "city": "hasilpur",
      "district": "bwp"
    },
    "items": [
      {
        "id": "item-7",
        "name": "Floral Print Maxi Dress",
        "image": "https://images.unsplash.com/photo-1572804013309-59a88b7e92f1?w=500&h=700&fit=crop",
        "price": "2900",
        "quantity": "1",
        "size": "M"
      },
      {
        "id": "item-2",
        "name": "Classic Cotton Kurta Set",
        "image": "https://images.unsplash.com/photo-1610030469983-98e550d6193c?w=500&h=700&fit=crop",
        "price": "2400",
        "quantity": "1",
        "size": "XL"
      },
      {
        "id": "item-wb2",
        "name": "Designer Tote Bag",
        "price": "4800",
        "image": "https://images.unsplash.com/photo-1584917865442-de89df76afd3?w=500&h=700&fit=crop",
        "quantity": "1",
        "size": ""
      }
    ],
    "total": "10100",
    "id": "ORD-1781609232950",
    "createdAt": "2026-06-16T11:27:12.950Z",
    "status": "New Order"
  },
  {
    "customer": {
      "name": "ZAHID HUSSAIN",
      "mobile": "03299931199",
      "email": "dripmobiles@gmail.com",
      "address": "shaili gharbi daak khana bakhshan khan tehsil chishtian",
      "city": "Bahawalnagar",
      "district": "bahawalpur"
    },
    "items": [
      {
        "id": "item-w1",
        "name": "Classic Gold Chronograph",
        "price": "9800",
        "image": "https://images.unsplash.com/photo-1524592094714-0f0654e20314?w=500&h=700&fit=crop",
        "quantity": "1",
        "size": ""
      }
    ],
    "total": "9800",
    "id": "ORD-1782006939480",
    "createdAt": "2026-06-21T01:55:39.480Z",
    "status": "New Order"
  }
]